odoo/addons/stock_available_to_promise_release_dynamic_routing/README.rst
odoo/addons/stock_available_to_promise_release_dynamic_routing/__init__.py
odoo/addons/stock_available_to_promise_release_dynamic_routing/__manifest__.py
odoo/addons/stock_available_to_promise_release_dynamic_routing/i18n/es_AR.po
odoo/addons/stock_available_to_promise_release_dynamic_routing/i18n/it.po
odoo/addons/stock_available_to_promise_release_dynamic_routing/i18n/pt_BR.po
odoo/addons/stock_available_to_promise_release_dynamic_routing/i18n/stock_available_to_promise_release_dynamic_routing.pot
odoo/addons/stock_available_to_promise_release_dynamic_routing/models/__init__.py
odoo/addons/stock_available_to_promise_release_dynamic_routing/models/stock_move.py
odoo/addons/stock_available_to_promise_release_dynamic_routing/readme/CONTRIBUTORS.rst
odoo/addons/stock_available_to_promise_release_dynamic_routing/readme/CREDITS.rst
odoo/addons/stock_available_to_promise_release_dynamic_routing/readme/DESCRIPTION.rst
odoo/addons/stock_available_to_promise_release_dynamic_routing/static/description/icon.png
odoo/addons/stock_available_to_promise_release_dynamic_routing/static/description/index.html
odoo/addons/stock_available_to_promise_release_dynamic_routing/tests/__init__.py
odoo/addons/stock_available_to_promise_release_dynamic_routing/tests/test_release_dynamic_routing.py
odoo14_addon_stock_available_to_promise_release_dynamic_routing-14.0.1.1.1.dev2.dist-info/METADATA
odoo14_addon_stock_available_to_promise_release_dynamic_routing-14.0.1.1.1.dev2.dist-info/WHEEL
odoo14_addon_stock_available_to_promise_release_dynamic_routing-14.0.1.1.1.dev2.dist-info/top_level.txt
odoo14_addon_stock_available_to_promise_release_dynamic_routing-14.0.1.1.1.dev2.dist-info/RECORD
